{
  "__inputs": [
    {
      "name": "DS_PROMETHEUS",
      "label": "Prometheus",
      "description": "",
      "type": "datasource",
      "pluginId": "prometheus",
      "pluginName": "Prometheus"
    }
  ],
  "__elements": {},
  "__requires": [
    {
      "type": "panel",
      "id": "bargauge",
      "name": "Bar gauge",
      "version": ""
    },
    {
      "type": "grafana",
      "id": "grafana",
      "name": "Grafana",
      "version": "12.4.1"
    },
    {
      "type": "datasource",
      "id": "prometheus",
      "name": "Prometheus",
      "version": "1.0.0"
    },
    {
      "type": "panel",
      "id": "stat",
      "name": "Stat",
      "version": ""
    },
    {
      "type": "panel",
      "id": "timeseries",
      "name": "Time series",
      "version": ""
    }
  ],
  "annotations": {
    "list": [
      {
        "builtIn": 1,
        "datasource": {
          "type": "grafana",
          "uid": "-- Grafana --"
        },
        "enable": true,
        "hide": true,
        "iconColor": "rgba(0, 211, 255, 1)",
        "name": "Annotations & Alerts",
        "target": {
          "limit": 100,
          "matchAny": false,
          "tags": [],
          "type": "dashboard"
        },
        "type": "dashboard"
      }
    ]
  },
  "description": "Полный мониторинг хоста: CPU, Память, Сеть, Диски, ФС (Node Exporter)",
  "editable": true,
  "fiscalYearStartMonth": 0,
  "graphTooltip": 1,
  "links": [],
  "panels": [
    {
      "collapsed": false,
      "gridPos": {
        "h": 1,
        "w": 24,
        "x": 0,
        "y": 0
      },
      "id": 20,
      "panels": [],
      "title": "Общая информация",
      "type": "row"
    },
    {
      "datasource": {
        "type": "prometheus",
        "uid": "${datasource}"
      },
      "fieldConfig": {
        "defaults": {
          "color": {
            "mode": "thresholds"
          },
          "mappings": [],
          "thresholds": {
            "mode": "absolute",
            "steps": [
              {
                "color": "green",
                "value": 0
              }
            ]
          },
          "unit": "s"
        },
        "overrides": []
      },
      "gridPos": {
        "h": 4,
        "w": 4,
        "x": 0,
        "y": 1
      },
      "id": 6,
      "options": {
        "colorMode": "value",
        "graphMode": "none",
        "justifyMode": "auto",
        "orientation": "auto",
        "percentChangeColorMode": "standard",
        "reduceOptions": {
          "calcs": [
            "lastNotNull"
          ],
          "fields": "",
          "values": false
        },
        "showPercentChange": false,
        "textMode": "auto",
        "wideLayout": true
      },
      "pluginVersion": "12.4.1",
      "targets": [
        {
          "expr": "time() - node_boot_time_seconds{instance=\"$instance\"}",
          "legendFormat": "Uptime",
          "refId": "A",
          "datasource": {
            "type": "prometheus",
            "uid": "${datasource}"
          }
        }
      ],
      "title": "Uptime (Время работы)",
      "type": "stat"
    },
    {
      "datasource": {
        "type": "prometheus",
        "uid": "${datasource}"
      },
      "fieldConfig": {
        "defaults": {
          "color": {
            "mode": "thresholds"
          },
          "mappings": [],
          "thresholds": {
            "mode": "absolute",
            "steps": [
              {
                "color": "green",
                "value": 0
              }
            ]
          },
          "unit": "short"
        },
        "overrides": []
      },
      "gridPos": {
        "h": 4,
        "w": 4,
        "x": 4,
        "y": 1
      },
      "id": 2,
      "options": {
        "colorMode": "value",
        "graphMode": "none",
        "justifyMode": "auto",
        "orientation": "auto",
        "percentChangeColorMode": "standard",
        "reduceOptions": {
          "calcs": [
            "lastNotNull"
          ],
          "fields": "",
          "values": false
        },
        "showPercentChange": false,
        "textMode": "auto",
        "wideLayout": true
      },
      "pluginVersion": "12.4.1",
      "targets": [
        {
          "expr": "count(node_cpu_seconds_total{instance=\"$instance\", mode='user'})",
          "legendFormat": "Cores",
          "refId": "A",
          "datasource": {
            "type": "prometheus",
            "uid": "${datasource}"
          }
        }
      ],
      "title": "CPU Cores",
      "type": "stat"
    },
    {
      "datasource": {
        "type": "prometheus",
        "uid": "${datasource}"
      },
      "fieldConfig": {
        "defaults": {
          "color": {
            "mode": "thresholds"
          },
          "mappings": [],
          "thresholds": {
            "mode": "absolute",
            "steps": [
              {
                "color": "green",
                "value": 0
              },
              {
                "color": "red",
                "value": 80
              }
            ]
          },
          "unit": "percent"
        },
        "overrides": []
      },
      "gridPos": {
        "h": 4,
        "w": 4,
        "x": 8,
        "y": 1
      },
      "id": 4,
      "options": {
        "colorMode": "value",
        "graphMode": "area",
        "justifyMode": "auto",
        "orientation": "auto",
        "percentChangeColorMode": "standard",
        "reduceOptions": {
          "calcs": [
            "lastNotNull"
          ],
          "fields": "",
          "values": false
        },
        "showPercentChange": false,
        "textMode": "auto",
        "wideLayout": true
      },
      "pluginVersion": "12.4.1",
      "targets": [
        {
          "expr": "100 - (avg(rate(node_cpu_seconds_total{instance=\"$instance\", mode=\"idle\"}[$__rate_interval])) * 100)",
          "legendFormat": "Usage",
          "refId": "A",
          "datasource": {
            "type": "prometheus",
            "uid": "${datasource}"
          }
        }
      ],
      "title": "CPU Usage",
      "type": "stat"
    },
    {
      "datasource": {
        "type": "prometheus",
        "uid": "${datasource}"
      },
      "fieldConfig": {
        "defaults": {
          "color": {
            "mode": "thresholds"
          },
          "mappings": [],
          "thresholds": {
            "mode": "absolute",
            "steps": [
              {
                "color": "green",
                "value": 0
              },
              {
                "color": "red",
                "value": 90
              }
            ]
          },
          "unit": "percent"
        },
        "overrides": []
      },
      "gridPos": {
        "h": 4,
        "w": 4,
        "x": 12,
        "y": 1
      },
      "id": 8,
      "options": {
        "colorMode": "value",
        "graphMode": "area",
        "justifyMode": "auto",
        "orientation": "auto",
        "percentChangeColorMode": "standard",
        "reduceOptions": {
          "calcs": [
            "lastNotNull"
          ],
          "fields": "",
          "values": false
        },
        "showPercentChange": false,
        "textMode": "auto",
        "wideLayout": true
      },
      "pluginVersion": "12.4.1",
      "targets": [
        {
          "expr": "((node_memory_MemTotal_bytes{instance=\"$instance\"} - node_memory_MemAvailable_bytes{instance=\"$instance\"}) / node_memory_MemTotal_bytes{instance=\"$instance\"}) * 100",
          "legendFormat": "RAM Usage",
          "refId": "A",
          "datasource": {
            "type": "prometheus",
            "uid": "${datasource}"
          }
        }
      ],
      "title": "RAM Usage",
      "type": "stat"
    },
    {
      "collapsed": false,
      "gridPos": {
        "h": 1,
        "w": 24,
        "x": 0,
        "y": 5
      },
      "id": 18,
      "panels": [],
      "title": "CPU",
      "type": "row"
    },
    {
      "datasource": {
        "type": "prometheus",
        "uid": "${datasource}"
      },
      "fieldConfig": {
        "defaults": {
          "color": {
            "mode": "palette-classic"
          },
          "custom": {
            "axisBorderShow": false,
            "axisCenteredZero": false,
            "axisColorMode": "text",
            "axisLabel": "",
            "axisPlacement": "auto",
            "axisSoftMax": 100,
            "barAlignment": 0,
            "barWidthFactor": 0.6,
            "drawStyle": "line",
            "fillOpacity": 10,
            "gradientMode": "none",
            "hideFrom": {
              "legend": false,
              "tooltip": false,
              "viz": false
            },
            "insertNulls": false,
            "lineInterpolation": "linear",
            "lineWidth": 1,
            "pointSize": 5,
            "scaleDistribution": {
              "type": "linear"
            },
            "showPoints": "auto",
            "showValues": false,
            "spanNulls": false,
            "stacking": {
              "group": "A",
              "mode": "none"
            },
            "thresholdsStyle": {
              "mode": "off"
            }
          },
          "mappings": [],
          "thresholds": {
            "mode": "absolute",
            "steps": [
              {
                "color": "green",
                "value": 0
              },
              {
                "color": "red",
                "value": 80
              }
            ]
          },
          "unit": "percent"
        },
        "overrides": []
      },
      "gridPos": {
        "h": 8,
        "w": 12,
        "x": 0,
        "y": 6
      },
      "id": 10,
      "options": {
        "legend": {
          "calcs": [],
          "displayMode": "list",
          "placement": "bottom",
          "showLegend": true
        },
        "tooltip": {
          "hideZeros": false,
          "mode": "multi",
          "sort": "none"
        }
      },
      "pluginVersion": "12.4.1",
      "targets": [
        {
          "expr": "100 - (avg(rate(node_cpu_seconds_total{instance=\"$instance\", mode=\"idle\"}[$__rate_interval])) * 100)",
          "legendFormat": "Total Usage",
          "refId": "A",
          "datasource": {
            "type": "prometheus",
            "uid": "${datasource}"
          }
        }
      ],
      "title": "Общая загрузка CPU",
      "type": "timeseries"
    },
    {
      "datasource": {
        "type": "prometheus",
        "uid": "${datasource}"
      },
      "fieldConfig": {
        "defaults": {
          "color": {
            "mode": "palette-classic"
          },
          "custom": {
            "axisBorderShow": false,
            "axisCenteredZero": false,
            "axisColorMode": "text",
            "axisLabel": "",
            "axisPlacement": "auto",
            "barAlignment": 0,
            "barWidthFactor": 0.6,
            "drawStyle": "line",
            "fillOpacity": 10,
            "gradientMode": "none",
            "hideFrom": {
              "legend": false,
              "tooltip": false,
              "viz": false
            },
            "insertNulls": false,
            "lineInterpolation": "linear",
            "lineWidth": 1,
            "pointSize": 5,
            "scaleDistribution": {
              "type": "linear"
            },
            "showPoints": "auto",
            "showValues": false,
            "spanNulls": false,
            "stacking": {
              "group": "A",
              "mode": "normal"
            },
            "thresholdsStyle": {
              "mode": "off"
            }
          },
          "mappings": [],
          "thresholds": {
            "mode": "absolute",
            "steps": [
              {
                "color": "green",
                "value": 0
              }
            ]
          },
          "unit": "percentunit"
        },
        "overrides": []
      },
      "gridPos": {
        "h": 8,
        "w": 12,
        "x": 12,
        "y": 6
      },
      "id": 12,
      "options": {
        "legend": {
          "calcs": [],
          "displayMode": "table",
          "placement": "right",
          "showLegend": true
        },
        "tooltip": {
          "hideZeros": false,
          "mode": "multi",
          "sort": "none"
        }
      },
      "pluginVersion": "12.4.1",
      "targets": [
        {
          "expr": "avg(rate(node_cpu_seconds_total{instance=\"$instance\", mode!=\"idle\"}[$__rate_interval])) by (mode)",
          "legendFormat": "{{mode}}",
          "refId": "A",
          "datasource": {
            "type": "prometheus",
            "uid": "${datasource}"
          }
        }
      ],
      "title": "CPU по режимам (Breakdown)",
      "type": "timeseries"
    },
    {
      "collapsed": false,
      "gridPos": {
        "h": 1,
        "w": 24,
        "x": 0,
        "y": 14
      },
      "id": 16,
      "panels": [],
      "title": "Память",
      "type": "row"
    },
    {
      "datasource": {
        "type": "prometheus",
        "uid": "${datasource}"
      },
      "fieldConfig": {
        "defaults": {
          "color": {
            "mode": "palette-classic"
          },
          "mappings": [],
          "thresholds": {
            "mode": "absolute",
            "steps": [
              {
                "color": "green",
                "value": 0
              },
              {
                "color": "red",
                "value": 80
              }
            ]
          },
          "unit": "bytes"
        },
        "overrides": []
      },
      "gridPos": {
        "h": 8,
        "w": 12,
        "x": 0,
        "y": 15
      },
      "id": 14,
      "options": {
        "displayMode": "gradient",
        "legend": {
          "calcs": [],
          "displayMode": "list",
          "placement": "bottom",
          "showLegend": false
        },
        "maxVizHeight": 300,
        "minVizHeight": 10,
        "minVizWidth": 0,
        "namePlacement": "auto",
        "orientation": "horizontal",
        "reduceOptions": {
          "calcs": [
            "lastNotNull"
          ],
          "fields": "",
          "values": false
        },
        "showUnfilled": true,
        "sizing": "auto",
        "text": {},
        "valueMode": "color"
      },
      "pluginVersion": "12.4.1",
      "targets": [
        {
          "expr": "node_memory_MemTotal_bytes{instance=\"$instance\"} - node_memory_MemAvailable_bytes{instance=\"$instance\"}",
          "legendFormat": "Used",
          "refId": "A",
          "datasource": {
            "type": "prometheus",
            "uid": "${datasource}"
          }
        },
        {
          "expr": "node_memory_MemAvailable_bytes{instance=\"$instance\"}",
          "legendFormat": "Available",
          "refId": "B",
          "datasource": {
            "type": "prometheus",
            "uid": "${datasource}"
          }
        }
      ],
      "title": "Использование RAM",
      "type": "bargauge"
    },
    {
      "datasource": {
        "type": "prometheus",
        "uid": "${datasource}"
      },
      "fieldConfig": {
        "defaults": {
          "color": {
            "mode": "palette-classic"
          },
          "custom": {
            "axisBorderShow": false,
            "axisCenteredZero": false,
            "axisColorMode": "text",
            "axisLabel": "",
            "axisPlacement": "auto",
            "barAlignment": 0,
            "barWidthFactor": 0.6,
            "drawStyle": "line",
            "fillOpacity": 10,
            "gradientMode": "none",
            "hideFrom": {
              "legend": false,
              "tooltip": false,
              "viz": false
            },
            "insertNulls": false,
            "lineInterpolation": "linear",
            "lineWidth": 1,
            "pointSize": 5,
            "scaleDistribution": {
              "type": "linear"
            },
            "showPoints": "auto",
            "showValues": false,
            "spanNulls": false,
            "stacking": {
              "group": "A",
              "mode": "normal"
            },
            "thresholdsStyle": {
              "mode": "off"
            }
          },
          "mappings": [],
          "min": 0,
          "thresholds": {
            "mode": "absolute",
            "steps": [
              {
                "color": "green",
                "value": 0
              }
            ]
          },
          "unit": "bytes"
        },
        "overrides": []
      },
      "gridPos": {
        "h": 8,
        "w": 12,
        "x": 12,
        "y": 15
      },
      "id": 22,
      "options": {
        "legend": {
          "calcs": [],
          "displayMode": "list",
          "placement": "bottom",
          "showLegend": true
        },
        "tooltip": {
          "hideZeros": false,
          "mode": "multi",
          "sort": "none"
        }
      },
      "pluginVersion": "12.4.1",
      "targets": [
        {
          "expr": "node_memory_MemTotal_bytes{instance=\"$instance\"} - node_memory_MemAvailable_bytes{instance=\"$instance\"}",
          "legendFormat": "Used",
          "refId": "A",
          "datasource": {
            "type": "prometheus",
            "uid": "${datasource}"
          }
        },
        {
          "expr": "node_memory_MemAvailable_bytes{instance=\"$instance\"}",
          "legendFormat": "Available",
          "refId": "B",
          "datasource": {
            "type": "prometheus",
            "uid": "${datasource}"
          }
        },
        {
          "expr": "node_memory_SwapTotal_bytes{instance=\"$instance\"} - node_memory_SwapFree_bytes{instance=\"$instance\"}",
          "legendFormat": "Swap Used",
          "refId": "C",
          "datasource": {
            "type": "prometheus",
            "uid": "${datasource}"
          }
        }
      ],
      "title": "Динамика памяти",
      "type": "timeseries"
    },
    {
      "collapsed": false,
      "gridPos": {
        "h": 1,
        "w": 24,
        "x": 0,
        "y": 23
      },
      "id": 24,
      "panels": [],
      "title": "Сеть",
      "type": "row"
    },
    {
      "datasource": {
        "type": "prometheus",
        "uid": "${datasource}"
      },
      "fieldConfig": {
        "defaults": {
          "color": {
            "mode": "palette-classic"
          },
          "custom": {
            "axisBorderShow": false,
            "axisCenteredZero": false,
            "axisColorMode": "text",
            "axisLabel": "",
            "axisPlacement": "auto",
            "barAlignment": 0,
            "barWidthFactor": 0.6,
            "drawStyle": "line",
            "fillOpacity": 10,
            "gradientMode": "none",
            "hideFrom": {
              "legend": false,
              "tooltip": false,
              "viz": false
            },
            "insertNulls": false,
            "lineInterpolation": "linear",
            "lineWidth": 1,
            "pointSize": 5,
            "scaleDistribution": {
              "type": "linear"
            },
            "showPoints": "auto",
            "showValues": false,
            "spanNulls": false,
            "stacking": {
              "group": "A",
              "mode": "none"
            },
            "thresholdsStyle": {
              "mode": "off"
            }
          },
          "mappings": [],
          "thresholds": {
            "mode": "absolute",
            "steps": [
              {
                "color": "green",
                "value": 0
              }
            ]
          },
          "unit": "bps"
        },
        "overrides": [
          {
            "matcher": {
              "id": "byName",
              "options": "Received"
            },
            "properties": [
              {
                "id": "color",
                "value": {
                  "fixedColor": "green",
                  "mode": "fixed"
                }
              }
            ]
          },
          {
            "matcher": {
              "id": "byName",
              "options": "Sent"
            },
            "properties": [
              {
                "id": "color",
                "value": {
                  "fixedColor": "blue",
                  "mode": "fixed"
                }
              }
            ]
          }
        ]
      },
      "gridPos": {
        "h": 8,
        "w": 24,
        "x": 0,
        "y": 24
      },
      "id": 26,
      "options": {
        "legend": {
          "calcs": [],
          "displayMode": "list",
          "placement": "bottom",
          "showLegend": true
        },
        "tooltip": {
          "hideZeros": false,
          "mode": "multi",
          "sort": "none"
        }
      },
      "pluginVersion": "12.4.1",
      "targets": [
        {
          "expr": "sum(rate(node_network_receive_bytes_total{instance=\"$instance\", device!=\"lo\"}[$__rate_interval])) by (instance)",
          "legendFormat": "Received",
          "refId": "A",
          "datasource": {
            "type": "prometheus",
            "uid": "${datasource}"
          }
        },
        {
          "expr": "sum(rate(node_network_transmit_bytes_total{instance=\"$instance\", device!=\"lo\"}[$__rate_interval])) by (instance)",
          "legendFormat": "Sent",
          "refId": "B",
          "datasource": {
            "type": "prometheus",
            "uid": "${datasource}"
          }
        }
      ],
      "title": "Сетевой трафик",
      "type": "timeseries"
    },
    {
      "collapsed": false,
      "gridPos": {
        "h": 1,
        "w": 24,
        "x": 0,
        "y": 32
      },
      "id": 28,
      "panels": [],
      "title": "Дисковый ввод-вывод (Disk I/O)",
      "type": "row"
    },
    {
      "datasource": {
        "type": "prometheus",
        "uid": "${datasource}"
      },
      "fieldConfig": {
        "defaults": {
          "color": {
            "mode": "palette-classic"
          },
          "custom": {
            "axisBorderShow": false,
            "axisCenteredZero": false,
            "axisColorMode": "text",
            "axisLabel": "",
            "axisPlacement": "auto",
            "barAlignment": 0,
            "barWidthFactor": 0.6,
            "drawStyle": "line",
            "fillOpacity": 10,
            "gradientMode": "none",
            "hideFrom": {
              "legend": false,
              "tooltip": false,
              "viz": false
            },
            "insertNulls": false,
            "lineInterpolation": "linear",
            "lineWidth": 1,
            "pointSize": 5,
            "scaleDistribution": {
              "type": "linear"
            },
            "showPoints": "auto",
            "showValues": false,
            "spanNulls": false,
            "stacking": {
              "group": "A",
              "mode": "none"
            },
            "thresholdsStyle": {
              "mode": "off"
            }
          },
          "mappings": [],
          "thresholds": {
            "mode": "absolute",
            "steps": [
              {
                "color": "green",
                "value": 0
              }
            ]
          },
          "unit": "Bps"
        },
        "overrides": [
          {
            "matcher": {
              "id": "byName",
              "options": "Read"
            },
            "properties": [
              {
                "id": "color",
                "value": {
                  "fixedColor": "green",
                  "mode": "fixed"
                }
              }
            ]
          },
          {
            "matcher": {
              "id": "byName",
              "options": "Write"
            },
            "properties": [
              {
                "id": "color",
                "value": {
                  "fixedColor": "red",
                  "mode": "fixed"
                }
              }
            ]
          }
        ]
      },
      "gridPos": {
        "h": 8,
        "w": 12,
        "x": 0,
        "y": 33
      },
      "id": 30,
      "options": {
        "legend": {
          "calcs": [],
          "displayMode": "list",
          "placement": "bottom",
          "showLegend": true
        },
        "tooltip": {
          "hideZeros": false,
          "mode": "multi",
          "sort": "none"
        }
      },
      "pluginVersion": "12.4.1",
      "targets": [
        {
          "expr": "sum(rate(node_disk_read_bytes_total{instance=\"$instance\", device=~\"$disk\"}[$__rate_interval])) by (device)",
          "legendFormat": "Read - {{device}}",
          "refId": "A",
          "datasource": {
            "type": "prometheus",
            "uid": "${datasource}"
          }
        },
        {
          "expr": "sum(rate(node_disk_written_bytes_total{instance=\"$instance\", device=~\"$disk\"}[$__rate_interval])) by (device)",
          "legendFormat": "Write - {{device}}",
          "refId": "B",
          "datasource": {
            "type": "prometheus",
            "uid": "${datasource}"
          }
        }
      ],
      "title": "Скорость чтения/записи (IOPS Throughput)",
      "type": "timeseries"
    },
    {
      "datasource": {
        "type": "prometheus",
        "uid": "${datasource}"
      },
      "fieldConfig": {
        "defaults": {
          "color": {
            "mode": "palette-classic"
          },
          "custom": {
            "axisBorderShow": false,
            "axisCenteredZero": false,
            "axisColorMode": "text",
            "axisLabel": "",
            "axisPlacement": "auto",
            "barAlignment": 0,
            "barWidthFactor": 0.6,
            "drawStyle": "line",
            "fillOpacity": 10,
            "gradientMode": "none",
            "hideFrom": {
              "legend": false,
              "tooltip": false,
              "viz": false
            },
            "insertNulls": false,
            "lineInterpolation": "linear",
            "lineWidth": 1,
            "pointSize": 5,
            "scaleDistribution": {
              "type": "linear"
            },
            "showPoints": "auto",
            "showValues": false,
            "spanNulls": false,
            "stacking": {
              "group": "A",
              "mode": "none"
            },
            "thresholdsStyle": {
              "mode": "off"
            }
          },
          "mappings": [],
          "thresholds": {
            "mode": "absolute",
            "steps": [
              {
                "color": "green",
                "value": 0
              }
            ]
          },
          "unit": "ops"
        },
        "overrides": [
          {
            "matcher": {
              "id": "byName",
              "options": "Read"
            },
            "properties": [
              {
                "id": "color",
                "value": {
                  "fixedColor": "green",
                  "mode": "fixed"
                }
              }
            ]
          },
          {
            "matcher": {
              "id": "byName",
              "options": "Write"
            },
            "properties": [
              {
                "id": "color",
                "value": {
                  "fixedColor": "red",
                  "mode": "fixed"
                }
              }
            ]
          }
        ]
      },
      "gridPos": {
        "h": 8,
        "w": 12,
        "x": 12,
        "y": 33
      },
      "id": 32,
      "options": {
        "legend": {
          "calcs": [],
          "displayMode": "list",
          "placement": "bottom",
          "showLegend": true
        },
        "tooltip": {
          "hideZeros": false,
          "mode": "multi",
          "sort": "none"
        }
      },
      "pluginVersion": "12.4.1",
      "targets": [
        {
          "expr": "sum(rate(node_disk_reads_completed_total{instance=\"$instance\", device=~\"$disk\"}[$__rate_interval])) by (device)",
          "legendFormat": "Read - {{device}}",
          "refId": "A",
          "datasource": {
            "type": "prometheus",
            "uid": "${datasource}"
          }
        },
        {
          "expr": "sum(rate(node_disk_writes_completed_total{instance=\"$instance\", device=~\"$disk\"}[$__rate_interval])) by (device)",
          "legendFormat": "Write - {{device}}",
          "refId": "B",
          "datasource": {
            "type": "prometheus",
            "uid": "${datasource}"
          }
        }
      ],
      "title": "Количество операций в секунду (IOPS)",
      "type": "timeseries"
    },
    {
      "datasource": {
        "type": "prometheus",
        "uid": "${datasource}"
      },
      "fieldConfig": {
        "defaults": {
          "color": {
            "mode": "thresholds"
          },
          "mappings": [],
          "thresholds": {
            "mode": "absolute",
            "steps": [
              {
                "color": "green",
                "value": 0
              },
              {
                "color": "yellow",
                "value": 100
              },
              {
                "color": "red",
                "value": 500
              }
            ]
          },
          "unit": "ms"
        },
        "overrides": []
      },
      "gridPos": {
        "h": 8,
        "w": 12,
        "x": 0,
        "y": 41
      },
      "id": 34,
      "options": {
        "displayMode": "gradient",
        "legend": {
          "calcs": [],
          "displayMode": "list",
          "placement": "bottom",
          "showLegend": false
        },
        "maxVizHeight": 300,
        "minVizHeight": 10,
        "minVizWidth": 0,
        "namePlacement": "auto",
        "orientation": "horizontal",
        "reduceOptions": {
          "calcs": [
            "lastNotNull"
          ],
          "fields": "",
          "values": false
        },
        "showUnfilled": true,
        "sizing": "auto",
        "text": {},
        "valueMode": "color"
      },
      "pluginVersion": "12.4.1",
      "targets": [
        {
          "expr": "avg(node_disk_io_time_seconds_total{instance=\"$instance\", device=~\"$disk\"}) by (device)",
          "legendFormat": "{{device}}",
          "refId": "A",
          "datasource": {
            "type": "prometheus",
            "uid": "${datasource}"
          }
        }
      ],
      "title": "Время ожидания ввода-вывода (I/O Time)",
      "type": "bargauge"
    },
    {
      "datasource": {
        "type": "prometheus",
        "uid": "${datasource}"
      },
      "fieldConfig": {
        "defaults": {
          "color": {
            "mode": "palette-classic"
          },
          "custom": {
            "axisBorderShow": false,
            "axisCenteredZero": false,
            "axisColorMode": "text",
            "axisLabel": "",
            "axisPlacement": "auto",
            "barAlignment": 0,
            "barWidthFactor": 0.6,
            "drawStyle": "line",
            "fillOpacity": 10,
            "gradientMode": "none",
            "hideFrom": {
              "legend": false,
              "tooltip": false,
              "viz": false
            },
            "insertNulls": false,
            "lineInterpolation": "linear",
            "lineWidth": 1,
            "pointSize": 5,
            "scaleDistribution": {
              "type": "linear"
            },
            "showPoints": "auto",
            "showValues": false,
            "spanNulls": false,
            "stacking": {
              "group": "A",
              "mode": "none"
            },
            "thresholdsStyle": {
              "mode": "off"
            }
          },
          "mappings": [],
          "thresholds": {
            "mode": "absolute",
            "steps": [
              {
                "color": "green",
                "value": 0
              }
            ]
          },
          "unit": "percent"
        },
        "overrides": []
      },
      "gridPos": {
        "h": 8,
        "w": 12,
        "x": 12,
        "y": 41
      },
      "id": 36,
      "options": {
        "legend": {
          "calcs": [],
          "displayMode": "list",
          "placement": "bottom",
          "showLegend": true
        },
        "tooltip": {
          "hideZeros": false,
          "mode": "multi",
          "sort": "none"
        }
      },
      "pluginVersion": "12.4.1",
      "targets": [
        {
          "expr": "rate(node_disk_io_time_seconds_total{instance=\"$instance\", device=~\"$disk\"}[$__rate_interval]) * 100",
          "legendFormat": "{{device}}",
          "refId": "A",
          "datasource": {
            "type": "prometheus",
            "uid": "${datasource}"
          }
        }
      ],
      "title": "Утилизация диска (Disk Utilization)",
      "type": "timeseries"
    },
    {
      "collapsed": false,
      "gridPos": {
        "h": 1,
        "w": 24,
        "x": 0,
        "y": 49
      },
      "id": 38,
      "panels": [],
      "title": "Файловая система (Filesystem)",
      "type": "row"
    },
    {
      "datasource": {
        "type": "prometheus",
        "uid": "${datasource}"
      },
      "fieldConfig": {
        "defaults": {
          "color": {
            "mode": "palette-classic"
          },
          "custom": {
            "axisBorderShow": false,
            "axisCenteredZero": false,
            "axisColorMode": "text",
            "axisLabel": "",
            "axisPlacement": "auto",
            "axisSoftMin": 0,
            "barAlignment": 0,
            "barWidthFactor": 0.6,
            "drawStyle": "line",
            "fillOpacity": 10,
            "gradientMode": "none",
            "hideFrom": {
              "legend": false,
              "tooltip": false,
              "viz": false
            },
            "insertNulls": false,
            "lineInterpolation": "linear",
            "lineWidth": 1,
            "pointSize": 5,
            "scaleDistribution": {
              "type": "linear"
            },
            "showPoints": "auto",
            "showValues": false,
            "spanNulls": false,
            "stacking": {
              "group": "A",
              "mode": "normal"
            },
            "thresholdsStyle": {
              "mode": "off"
            }
          },
          "mappings": [],
          "thresholds": {
            "mode": "absolute",
            "steps": [
              {
                "color": "green",
                "value": 0
              }
            ]
          },
          "unit": "bytes"
        },
        "overrides": []
      },
      "gridPos": {
        "h": 8,
        "w": 24,
        "x": 0,
        "y": 50
      },
      "id": 44,
      "options": {
        "legend": {
          "calcs": [],
          "displayMode": "table",
          "placement": "right",
          "showLegend": true
        },
        "tooltip": {
          "hideZeros": false,
          "mode": "multi",
          "sort": "none"
        }
      },
      "pluginVersion": "12.4.1",
      "targets": [
        {
          "editorMode": "code",
          "expr": "node_filesystem_size_bytes{instance=\"$instance\", fstype!=\"\", mountpoint!=\"\", mountpoint!~\"/(boot|run|nix).*\"} - node_filesystem_avail_bytes{instance=\"$instance\", fstype!=\"\", mountpoint!=\"\", mountpoint!~\"/boot.*\", mountpoint!~\"/(boot|run|nix).*\"}",
          "legendFormat": "Used - {{mountpoint}}",
          "range": true,
          "refId": "A",
          "datasource": {
            "type": "prometheus",
            "uid": "${datasource}"
          }
        },
        {
          "editorMode": "code",
          "expr": "node_filesystem_avail_bytes{instance=\"$instance\", fstype!=\"\", mountpoint!=\"\", mountpoint!~\"/(boot|run|nix).*\"}",
          "legendFormat": "Free - {{mountpoint}}",
          "range": true,
          "refId": "B",
          "datasource": {
            "type": "prometheus",
            "uid": "${datasource}"
          }
        }
      ],
      "title": "Динамика использования ФС",
      "type": "timeseries"
    }
  ],
  "preload": false,
  "refresh": "30s",
  "schemaVersion": 42,
  "tags": [
    "node-exporter",
    "host",
    "linux",
    "disk",
    "filesystem"
  ],
  "templating": {
    "list": [
      {
        "current": {
          "text": "",
          "value": "${DS_PROMETHEUS}",
          "selected": true
        },
        "includeAll": false,
        "label": "Datasource",
        "name": "datasource",
        "options": [],
        "query": "prometheus",
        "refresh": 1,
        "regex": "",
        "type": "datasource"
      },
      {
        "current": {},
        "datasource": {
          "type": "prometheus",
          "uid": "${datasource}"
        },
        "definition": "label_values(node_boot_time_seconds, instance)",
        "includeAll": false,
        "label": "Instance",
        "name": "instance",
        "options": [],
        "query": {
          "query": "label_values(node_boot_time_seconds, instance)",
          "refId": "PrometheusVariableQueryEditor-VariableQuery"
        },
        "refresh": 1,
        "regex": "",
        "regexApplyTo": "value",
        "sort": 1,
        "type": "query"
      },
      {
        "allValue": ".*",
        "current": {},
        "datasource": {
          "type": "prometheus",
          "uid": "${datasource}"
        },
        "definition": "label_values(node_disk_read_bytes_total{instance=\"$instance\"}, device)",
        "includeAll": true,
        "label": "Disk Device",
        "multi": true,
        "name": "disk",
        "options": [],
        "query": {
          "query": "label_values(node_disk_read_bytes_total{instance=\"$instance\"}, device)",
          "refId": "PrometheusVariableQueryEditor-VariableQuery"
        },
        "refresh": 1,
        "regex": "",
        "regexApplyTo": "value",
        "sort": 1,
        "type": "query"
      }
    ]
  },
  "time": {
    "from": "now-3h",
    "to": "now"
  },
  "timepicker": {},
  "timezone": "browser",
  "title": "Host Metrics (Full: CPU, Memory, Network, Disk I/O, Filesystem)",
  "uid": "host-metrics-full",
  "version": 6,
  "weekStart": ""
}
